markbassmodel/__init__.py
markbassmodel/markbassmodel.py
markbassmodel-0.1.1.dist-info/AUTHORS.rst
markbassmodel-0.1.1.dist-info/LICENSE
markbassmodel-0.1.1.dist-info/METADATA
markbassmodel-0.1.1.dist-info/WHEEL
markbassmodel-0.1.1.dist-info/top_level.txt
markbassmodel-0.1.1.dist-info/RECORD
