Metadata-Version: 2.1
Name: markbassmodel
Version: 0.1.1
Summary: This is a package containing several bass model functions that are useful for solving or evaluating marketing related problems 
Home-page: https://github.com/anukzak22/markbassmodel
Author: Anahit Zakaryan
Author-email: anukzak@gmail.com
License: MIT license
Keywords: markbassmodel
Classifier: Development Status :: 2 - Pre-Alpha
Classifier: Intended Audience :: Developers
Classifier: License :: OSI Approved :: MIT License
Classifier: Natural Language :: English
Classifier: Programming Language :: Python :: 3
Classifier: Programming Language :: Python :: 3.6
Classifier: Programming Language :: Python :: 3.7
Classifier: Programming Language :: Python :: 3.8
Requires-Python: >=3.6
License-File: LICENSE
License-File: AUTHORS.rst
